neuranet/__init__.py
neuranet/neuranet.py
neuranet-0.0.1.dist-info/METADATA
neuranet-0.0.1.dist-info/WHEEL
neuranet-0.0.1.dist-info/top_level.txt
neuranet-0.0.1.dist-info/RECORD
