Metadata-Version: 2.1
Name: neuranet
Version: 0.0.1
Summary: NeuraNET Python API library
Author: Dark25 (Ruben Roy)
Author-email: me@ruben-roy.com
Keywords: ai,machine learning,neuranet
Classifier: Development Status :: 3 - Alpha
Classifier: Intended Audience :: Developers
Classifier: License :: OSI Approved :: MIT License
Classifier: Programming Language :: Python :: 3
Classifier: Programming Language :: Python :: 3.6
Classifier: Programming Language :: Python :: 3.7
Classifier: Programming Language :: Python :: 3.8
Classifier: Programming Language :: Python :: 3.9
Requires-Dist: requests
